pytest_line_profiler_apn.py
pytest_line_profiler_apn-0.1.5.dist-info/entry_points.txt
pytest_line_profiler_apn-0.1.5.dist-info/LICENSE
pytest_line_profiler_apn-0.1.5.dist-info/WHEEL
pytest_line_profiler_apn-0.1.5.dist-info/METADATA
pytest_line_profiler_apn-0.1.5.dist-info/RECORD
