Metadata-Version: 2.1
Name: pytest-line-profiler-apn
Version: 0.1.5
Summary: Profile code executed by pytest
Author: Martín Gaitán
Author-email: gaitan@gmail.com
Maintainer: Alexander Puck Neuwirth
Maintainer-email: alexander@neuwirth-informatik.de
Requires-Python: >=3.8,<4.0
Classifier: Programming Language :: Python :: 3
Classifier: Programming Language :: Python :: 3.8
Classifier: Programming Language :: Python :: 3.9
Classifier: Programming Language :: Python :: 3.10
Classifier: Programming Language :: Python :: 3.11
Requires-Dist: line-profiler
Requires-Dist: pytest (>=3.5.0)
